LICENSE.txt
MANIFEST.in
README.md
setup.cfg
setup.py
django_post_deploy.egg-info/PKG-INFO
django_post_deploy.egg-info/SOURCES.txt
django_post_deploy.egg-info/dependency_links.txt
django_post_deploy.egg-info/requires.txt
django_post_deploy.egg-info/top_level.txt
post_deploy/__init__.py
post_deploy/errors.py
post_deploy/local_utils.py
post_deploy/models.py
post_deploy/tasks.py
post_deploy/utils.py
post_deploy/management/commands/deploy.py
post_deploy/migrations/0001_initial.py
post_deploy/migrations/0002_postdeploylog.py
post_deploy/migrations/__init__.py
post_deploy/plugins/__init__.py
post_deploy/plugins/context/__init__.py
post_deploy/plugins/context/tenant.py
post_deploy/plugins/scheduler/__init__.py
post_deploy/plugins/scheduler/celery.py
post_deploy/tests/__init__.py
post_deploy/tests/test_decorator.py
post_deploy/tests/test_log_queryset.py
post_deploy/tests/test_management_command.py