Metadata-Version: 2.1
Name: django-post-deploy
Version: 2.4.5
Summary: Django post-deployment utility
Author: Erlend ter Maat
Author-email: erwitema@gmail.com
License: cc-by-4.0
Keywords: Django,Deployment,Management,CLI
Classifier: Development Status :: 5 - Production/Stable
Classifier: Intended Audience :: Developers
Classifier: Programming Language :: Python :: 3
Classifier: Programming Language :: Python :: 3.9
Classifier: Programming Language :: Python :: 3.10
Classifier: Programming Language :: Python :: 3.11
License-File: LICENSE.txt
Requires-Dist: Django
